setup.py
django_conch/__init__.py
django_conch/checker.py
django_conch/models.py
django_conch.egg-info/PKG-INFO
django_conch.egg-info/SOURCES.txt
django_conch.egg-info/dependency_links.txt
django_conch.egg-info/requires.txt
django_conch.egg-info/top_level.txt
django_conch/management/__init__.py
django_conch/management/commands/__init__.py
django_conch/management/commands/conch.py