Metadata-Version: 1.0
Name: django-conch
Version: 0.0.1
Summary: Expose the Django shell as an SSH server.
Home-page: https://github.com/zacharyvoase/django-conch
Author: Zachary Voase
Author-email: z@zacharyvoase.com
License: UNKNOWN
Platform: UNKNOWN
